CHANGES
MANIFEST.in
README.rst
setup.py
isotoma/__init__.py
isotoma.zope.groupreadableblobstorage.egg-info/PKG-INFO
isotoma.zope.groupreadableblobstorage.egg-info/SOURCES.txt
isotoma.zope.groupreadableblobstorage.egg-info/dependency_links.txt
isotoma.zope.groupreadableblobstorage.egg-info/entry_points.txt
isotoma.zope.groupreadableblobstorage.egg-info/namespace_packages.txt
isotoma.zope.groupreadableblobstorage.egg-info/not-zip-safe
isotoma.zope.groupreadableblobstorage.egg-info/requires.txt
isotoma.zope.groupreadableblobstorage.egg-info/top_level.txt
isotoma/zope/__init__.py
isotoma/zope/groupreadableblobstorage/__init__.py
isotoma/zope/groupreadableblobstorage/component.xml