Metadata-Version: 1.0
Name: isotoma.zope.groupreadableblobstorage
Version: 0.0.4
Summary: Make blob storage group readable
Home-page: http://github.com/isotoma/isotoma.zope.groupreadableblobstorage
Author: John Carr
Author-email: john.carr@isotoma.com
License: UNKNOWN
Platform: UNKNOWN
